XAnimePorn/XAnimePorn.py
XAnimePorn/__init__.py
XAnimePorn-1.2.dist-info/LICENSE
XAnimePorn-1.2.dist-info/METADATA
XAnimePorn-1.2.dist-info/WHEEL
XAnimePorn-1.2.dist-info/top_level.txt
XAnimePorn-1.2.dist-info/RECORD
