Metadata-Version: 2.1
Name: XAnimePorn
Version: 1.2
Summary: A simple scraper for the XAnimePorn.com website.
Home-page: https://github.com/elpideus/XAnimePorn
Author: Stefan Cucoranu
Author-email: elpideus@gmail.com
License: GNU General Public License v3 or later (GPLv3+)
Project-URL: Bug Tracker, https://github.com/elpideus/XAnimePorn/issues
Project-URL: Source Code, https://github.com/elpideus/XAnimePorn
Keywords: ['HENTAI','ANIME','XXX','PORN','OVERAGE']
Platform: UNKNOWN
Classifier: Development Status :: 5 - Production/Stable
Classifier: Intended Audience :: Developers
Classifier: Programming Language :: Python :: 3
Classifier: License :: OSI Approved :: GNU General Public License v3 or later (GPLv3+)
Classifier: Operating System :: OS Independent
Classifier: Programming Language :: Python :: 3.9
Requires-Python: >=3.4
License-File: LICENSE
